pyscolortext/__init__.py
pyscolortext-0.0.1.dist-info/METADATA
pyscolortext-0.0.1.dist-info/WHEEL
pyscolortext-0.0.1.dist-info/top_level.txt
pyscolortext-0.0.1.dist-info/RECORD
