Metadata-Version: 2.1
Name: pyscolortext
Version: 0.0.1
Summary: A library for colored text
Home-page: https://github.com/roshanlam/PyCT
Download-URL: https://github.com/roshanlam/PyCT/blob/main/dist/PyColorText-0.0.1.tar.gz
Author: roshanlam
Classifier: Development Status :: 5 - Production/Stable
Classifier: Intended Audience :: Developers
Classifier: Topic :: Software Development :: Build Tools
Classifier: License :: OSI Approved :: MIT License
Classifier: Programming Language :: Python :: 3
Classifier: Programming Language :: Python :: 3.4
Classifier: Programming Language :: Python :: 3.5
Classifier: Programming Language :: Python :: 3.6
Classifier: Programming Language :: Python :: 3.7
